endstone_qqsync_plugin/__init__.py
endstone_qqsync_plugin/qqsync_plugin.py
endstone_qqsync_plugin/core/__init__.py
endstone_qqsync_plugin/core/config_manager.py
endstone_qqsync_plugin/core/data_manager.py
endstone_qqsync_plugin/core/event_handlers.py
endstone_qqsync_plugin/core/permission_manager.py
endstone_qqsync_plugin/core/verification_manager.py
endstone_qqsync_plugin/lib/websockets/__init__.py
endstone_qqsync_plugin/lib/websockets/__main__.py
endstone_qqsync_plugin/lib/websockets/auth.py
endstone_qqsync_plugin/lib/websockets/cli.py
endstone_qqsync_plugin/lib/websockets/client.py
endstone_qqsync_plugin/lib/websockets/connection.py
endstone_qqsync_plugin/lib/websockets/datastructures.py
endstone_qqsync_plugin/lib/websockets/exceptions.py
endstone_qqsync_plugin/lib/websockets/frames.py
endstone_qqsync_plugin/lib/websockets/headers.py
endstone_qqsync_plugin/lib/websockets/http.py
endstone_qqsync_plugin/lib/websockets/http11.py
endstone_qqsync_plugin/lib/websockets/imports.py
endstone_qqsync_plugin/lib/websockets/protocol.py
endstone_qqsync_plugin/lib/websockets/py.typed
endstone_qqsync_plugin/lib/websockets/server.py
endstone_qqsync_plugin/lib/websockets/speedups.c
endstone_qqsync_plugin/lib/websockets/speedups.pyi
endstone_qqsync_plugin/lib/websockets/streams.py
endstone_qqsync_plugin/lib/websockets/typing.py
endstone_qqsync_plugin/lib/websockets/uri.py
endstone_qqsync_plugin/lib/websockets/utils.py
endstone_qqsync_plugin/lib/websockets/version.py
endstone_qqsync_plugin/lib/websockets/asyncio/__init__.py
endstone_qqsync_plugin/lib/websockets/asyncio/async_timeout.py
endstone_qqsync_plugin/lib/websockets/asyncio/client.py
endstone_qqsync_plugin/lib/websockets/asyncio/compatibility.py
endstone_qqsync_plugin/lib/websockets/asyncio/connection.py
endstone_qqsync_plugin/lib/websockets/asyncio/messages.py
endstone_qqsync_plugin/lib/websockets/asyncio/router.py
endstone_qqsync_plugin/lib/websockets/asyncio/server.py
endstone_qqsync_plugin-0.1.2.dist-info/METADATA
endstone_qqsync_plugin-0.1.2.dist-info/WHEEL
endstone_qqsync_plugin-0.1.2.dist-info/entry_points.txt
endstone_qqsync_plugin-0.1.2.dist-info/RECORD
