Metadata-Version: 2.4
Name: endstone-qqsync-plugin
Version: 0.1.2
Summary: Endstone QQsync群服互通插件 - 支持双向消息同步、服务器信息查询、管理命令执行
Project-URL: Homepage, https://github.com/yuexps/endstone-qqsync-plugin
Author-email: yuexps <yuexps@qq.com>
Requires-Python: >=3.11
